tpcav/__init__.py
tpcav/cavs.py
tpcav/concepts.py
tpcav/helper.py
tpcav/logging_utils.py
tpcav/tpcav_model.py
tpcav/utils.py
tpcav-0.1.0.dist-info/licenses/LICENSE
tpcav-0.1.0.dist-info/METADATA
tpcav-0.1.0.dist-info/WHEEL
tpcav-0.1.0.dist-info/top_level.txt
tpcav-0.1.0.dist-info/RECORD
