Metadata-Version: 2.4
Name: tpcav
Version: 0.1.0
Summary: Testing with PCA projected Concept Activation Vectors
Author-email: Jianyu Yang <yztxwd@gmail.com>
License-Expression: MIT AND (Apache-2.0 OR BSD-2-Clause)
Project-URL: Homepage, https://github.com/seqcode/TPCAV
Keywords: interpretation,attribution,concept,genomics,deep learning
Requires-Python: >=3.8
License-File: LICENSE
Requires-Dist: torch
Requires-Dist: pandas
Requires-Dist: numpy
Requires-Dist: seqchromloader
Requires-Dist: deeplift
Requires-Dist: pyfaidx
Requires-Dist: pybedtools
Requires-Dist: captum
Requires-Dist: scikit-learn
Requires-Dist: biopython
Requires-Dist: seaborn
Requires-Dist: matplotlib
Dynamic: license-file
